Metadata-Version: 2.1
Name: awsneo
Version: 0.0.1
Summary: Library for python 3 that allows you to connect to different database engines (PostgreSQL, MySQL, MSSQL) through secrets manager (secret values) or direct connection, also allows you to execute queries from scripts in buckets or directly as a single query
Home-page: UNKNOWN
Author: Juan Rueda
Author-email: Juan.Rueda@btgpactual.com
License: UNKNOWN
Download-URL: https://github.com/jprugo/awsneo/archive/refs/tags/0.0.1.tar.gz
Platform: UNKNOWN
License-File: LICENSE.txt
